ZaidPP/ZaidPP.py
ZaidPP/__init__.py
ZaidPP-0.4.1.dist-info/LICENSE.txt
ZaidPP-0.4.1.dist-info/METADATA
ZaidPP-0.4.1.dist-info/WHEEL
ZaidPP-0.4.1.dist-info/top_level.txt
ZaidPP-0.4.1.dist-info/RECORD
