Metadata-Version: 2.1
Name: ZaidPP
Version: 0.4.1
Summary: • Scrape Instagram Profile and login Instagram
Home-page: 
Author: Zaid
Author-email: www710700@gmail.com
Project-URL: Bug Tracker, https://github.com/pypa/sampleproject/issues
Classifier: Programming Language :: Python :: 3
Classifier: License :: OSI Approved :: MIT License
Classifier: Operating System :: OS Independent
Requires-Python: >=3.8
License-File: LICENSE.txt
